Metadata-Version: 2.1
Name: imitation-qjm
Version: 0.1.dev188172685
Summary: Implementation of modern reward and imitation learning algorithms.
Home-page: https://github.com/HumanCompatibleAI/imitation
Author: Center for Human-Compatible AI and Google
License: MIT
Platform: UNKNOWN
Classifier: License :: OSI Approved :: MIT License
Classifier: Programming Language :: Python
Classifier: Programming Language :: Python :: 3
Classifier: Programming Language :: Python :: 3.8
Classifier: Programming Language :: Python :: 3.9
Classifier: Programming Language :: Python :: 3.10
Classifier: Programming Language :: Python :: Implementation :: CPython
Classifier: Programming Language :: Python :: Implementation :: PyPy
Requires-Python: >=3.8.0
License-File: LICENSE
Requires-Dist: datasets>=2.8.0
Requires-Dist: gymnasium[classic-control]~=0.29
Requires-Dist: huggingface-sb3~=3.0
Requires-Dist: matplotlib
Requires-Dist: numpy
Requires-Dist: optuna>=3.0.1
Requires-Dist: rich
Requires-Dist: sacred>=0.8.4
Requires-Dist: scikit-learn
Requires-Dist: seals~=0.2.1
Requires-Dist: stable-baselines3
Requires-Dist: tensorboard
Requires-Dist: torch
Requires-Dist: tqdm
Provides-Extra: atari
Requires-Dist: seals[atari]~=0.2.1; extra == "atari"
Provides-Extra: dev
Requires-Dist: autopep8; extra == "dev"
Requires-Dist: black[jupyter]~=22.6.0; extra == "dev"
Requires-Dist: codecov~=2.1.12; extra == "dev"
Requires-Dist: codespell; extra == "dev"
Requires-Dist: codespell~=2.1.0; extra == "dev"
Requires-Dist: coverage~=6.4.2; extra == "dev"
Requires-Dist: darglint~=1.8.1; extra == "dev"
Requires-Dist: filelock~=3.7.1; extra == "dev"
Requires-Dist: flake8-blind-except==0.2.1; extra == "dev"
Requires-Dist: flake8-builtins~=1.5.3; extra == "dev"
Requires-Dist: flake8-commas~=2.1.0; extra == "dev"
Requires-Dist: flake8-debugger~=4.1.2; extra == "dev"
Requires-Dist: flake8-docstrings~=1.6.0; extra == "dev"
Requires-Dist: flake8-isort~=4.1.2; extra == "dev"
Requires-Dist: flake8~=4.0.1; extra == "dev"
Requires-Dist: furo==2022.6.21; extra == "dev"
Requires-Dist: hypothesis~=6.54.1; extra == "dev"
Requires-Dist: ipdb; extra == "dev"
Requires-Dist: ipykernel~=6.15.1; extra == "dev"
Requires-Dist: ipykernel~=6.15.2; extra == "dev"
Requires-Dist: isort~=5.0; extra == "dev"
Requires-Dist: jupyter-client~=6.1.12; extra == "dev"
Requires-Dist: jupyter~=1.0.0; extra == "dev"
Requires-Dist: moviepy~=1.0.3; extra == "dev"
Requires-Dist: mypy~=0.990; extra == "dev"
Requires-Dist: myst-nb==0.17.2; extra == "dev"
Requires-Dist: pandas~=1.4.3; extra == "dev"
Requires-Dist: pre-commit>=2.20.0; extra == "dev"
Requires-Dist: pytest-cov~=3.0.0; extra == "dev"
Requires-Dist: pytest-notebook==0.8.0; extra == "dev"
Requires-Dist: pytest-timeout~=2.1.0; extra == "dev"
Requires-Dist: pytest-xdist~=2.5.0; extra == "dev"
Requires-Dist: pytest~=7.1.2; extra == "dev"
Requires-Dist: pytype==2023.9.27; extra == "dev"
Requires-Dist: ray[debug,tune]~=2.0.0; extra == "dev"
Requires-Dist: scipy~=1.9.0; extra == "dev"
Requires-Dist: seals[atari]~=0.2.1; extra == "dev"
Requires-Dist: setuptools-scm~=7.0.5; extra == "dev"
Requires-Dist: sphinx-autobuild; extra == "dev"
Requires-Dist: sphinx-autodoc-typehints~=1.19.1; extra == "dev"
Requires-Dist: sphinx-copybutton==0.5.0; extra == "dev"
Requires-Dist: sphinx-github-changelog~=1.2.0; extra == "dev"
Requires-Dist: sphinx-rtd-theme~=1.0.0; extra == "dev"
Requires-Dist: sphinxcontrib-napoleon==0.7; extra == "dev"
Requires-Dist: sphinx~=5.1.1; extra == "dev"
Requires-Dist: wandb==0.12.21; extra == "dev"
Provides-Extra: docs
Requires-Dist: furo==2022.6.21; extra == "docs"
Requires-Dist: hypothesis~=6.54.1; extra == "docs"
Requires-Dist: ipykernel~=6.15.2; extra == "docs"
Requires-Dist: myst-nb==0.17.2; extra == "docs"
Requires-Dist: ray[debug,tune]~=2.0.0; extra == "docs"
Requires-Dist: seals[atari]~=0.2.1; extra == "docs"
Requires-Dist: sphinx-autodoc-typehints~=1.19.1; extra == "docs"
Requires-Dist: sphinx-copybutton==0.5.0; extra == "docs"
Requires-Dist: sphinx-github-changelog~=1.2.0; extra == "docs"
Requires-Dist: sphinx-rtd-theme~=1.0.0; extra == "docs"
Requires-Dist: sphinxcontrib-napoleon==0.7; extra == "docs"
Requires-Dist: sphinx~=5.1.1; extra == "docs"
Provides-Extra: mujoco
Requires-Dist: gymnasium[classic-control,mujoco]~=0.29; extra == "mujoco"
Provides-Extra: parallel
Requires-Dist: ray[debug,tune]~=2.0.0; extra == "parallel"
Provides-Extra: test
Requires-Dist: black[jupyter]~=22.6.0; extra == "test"
Requires-Dist: codecov~=2.1.12; extra == "test"
Requires-Dist: codespell~=2.1.0; extra == "test"
Requires-Dist: coverage~=6.4.2; extra == "test"
Requires-Dist: darglint~=1.8.1; extra == "test"
Requires-Dist: filelock~=3.7.1; extra == "test"
Requires-Dist: flake8-blind-except==0.2.1; extra == "test"
Requires-Dist: flake8-builtins~=1.5.3; extra == "test"
Requires-Dist: flake8-commas~=2.1.0; extra == "test"
Requires-Dist: flake8-debugger~=4.1.2; extra == "test"
Requires-Dist: flake8-docstrings~=1.6.0; extra == "test"
Requires-Dist: flake8-isort~=4.1.2; extra == "test"
Requires-Dist: flake8~=4.0.1; extra == "test"
Requires-Dist: hypothesis~=6.54.1; extra == "test"
Requires-Dist: ipykernel~=6.15.1; extra == "test"
Requires-Dist: jupyter-client~=6.1.12; extra == "test"
Requires-Dist: jupyter~=1.0.0; extra == "test"
Requires-Dist: moviepy~=1.0.3; extra == "test"
Requires-Dist: mypy~=0.990; extra == "test"
Requires-Dist: pandas~=1.4.3; extra == "test"
Requires-Dist: pre-commit>=2.20.0; extra == "test"
Requires-Dist: pytest-cov~=3.0.0; extra == "test"
Requires-Dist: pytest-notebook==0.8.0; extra == "test"
Requires-Dist: pytest-timeout~=2.1.0; extra == "test"
Requires-Dist: pytest-xdist~=2.5.0; extra == "test"
Requires-Dist: pytest~=7.1.2; extra == "test"
Requires-Dist: pytype==2023.9.27; extra == "test"
Requires-Dist: ray[debug,tune]~=2.0.0; extra == "test"
Requires-Dist: scipy~=1.9.0; extra == "test"
Requires-Dist: seals[atari]~=0.2.1; extra == "test"
Requires-Dist: setuptools-scm~=7.0.5; extra == "test"
Requires-Dist: wandb==0.12.21; extra == "test"
